[
    {
        "type": "paragraph",
        "text_fr": "<!-- image -->",
        "text_en": "<!-- image -->"
    },
    {
        "type": "paragraph",
        "text_fr": "Distr. générale 29 mars 2021",
        "text_en": "Distr.: General 29 March 2021"
    },
    {
        "type": "paragraph",
        "text_fr": "Soixante-quinzième session Point 56 de l'ordre du jour",
        "text_en": "Agenda item 56"
    },
    {
        "type": "paragraph",
        "text_fr": "Questions relatives à l'information",
        "text_en": "Questions relating to information"
    },
    {
        "type": "heading",
        "level": 2,
        "text_fr": "Résolution adoptée par l'Assemblée générale le 25 mars 2021",
        "text_en": "Resolution adopted by the General Assembly on 25 March 2021"
    },
    {
        "type": "paragraph",
        "text_fr": "[ sans renvoi à une grande commission (A/75/L.68 et A/75/L.68/Add.1) ]",
        "text_en": "[without reference to a Main Committee (A/75/L.68 and A/75/L.68/Add.1) ]"
    },
    {
        "type": "heading",
        "level": 2,
        "text_fr": "75/267. Semaine mondiale de l'éducation aux médias et à l'information",
        "text_en": "75/267. World Media and Information Week"
    },
    {
        "type": "heading",
        "level": 2,
        "text_fr": "L'Assemblée générale ,",
        "text_en": "The General Assembly,"
    },
    {
        "type": "paragraph",
        "text_fr": "Réaffirmant les buts et principes consacrés par la Charte des Nations Unies et la Déclaration universelle des droits de l'homme 1 ,",
        "text_en": "Reaffirming the purposes and principles enshrined in the Charter of the United Nations and the Universal Declaration of Human Rights, 1"
    },
    {
        "type": "paragraph",
        "text_fr": "Rappelant l'article  19  du  Pacte  international  relatif  aux  droits  civils  et politiques 2 et  l'article  13  du  Pacte  international  relatif  aux  droits  économiques, sociaux et culturels 3 ,",
        "text_en": "Recalling article 19 of the International Covenant on Civil and Political Rights 2 and article 13 of the International Covenant on Economic, Social and Cultural Rights 3 ,"
    },
    {
        "type": "paragraph",
        "text_fr": "Rappelant  également ses  résolutions  75/101 A  et  75/101 B,  toutes  deux  du 10 décembre  2020,  respectivement  intitulées  « L'information  au  service  de l'humanité »  et  « Politiques  et  activités  de  l'Organisation  des  Nations  Unies  en matière de communication globale »,",
        "text_en": "Recalling also its resolutions 75/101 A and 75/101 B, both of 10 December 2020, entitled \"Information for humanity\" and \"United Nations policies and activities in the field of global communication\","
    },
    {
        "type": "paragraph",
        "text_fr": "Rappelant en outre sa  résolution  75/202  du  21  décembre  2020,  dans  laquelle elle  a  considéré  que  chaque  personne  devait  avoir  les  compétences  de  base indispensables dans les domaines des médias et de l'information et s'est félicitée de la tenue de la Semaine mondiale de l'éducation aux médias et à l'information du 24 au 31 octobre 2020,",
        "text_en": "Recalling further its resolution 75/202 of 21 December 2020, in which it considered that everyone should have the necessary basic media and information skills, and welcomed the holding of World Media and Public Information Week from 24 to 31 October 2020,"
    },
    {
        "type": "paragraph",
        "text_fr": "Prenant note avec satisfaction de la résolution 56 adoptée à l'unanimité par la Conférence générale de l'Organisation des Nations Unies pour l'éducation, la science et  la  culture  le  25  novembre  2019,  à  sa  quarantième  session,  dans  laquelle  a  été proclamée la Semaine mondiale de l'éducation aux médias et à l'information, qui se tient chaque année du 24 au 31 octobre 4 ,",
        "text_en": "Taking note with appreciation of resolution 56 unanimously adopted by the General Conference of the United Nations Educational, Scientific and Cultural Organization on 25 November 2019, at its fortieth session, in which the World Media and Information Week was proclaimed every year from 24 to 31 October 4,"
    },
    {
        "type": "paragraph",
        "text_fr": "\\_\\_\\_\\_\\_\\_\\_\\_\\_\\_\\_\\_\\_\\_\\_\\_\\_\\_",
        "text_en": "\\_\\_\\_\\_\\_\\_\\_\\_\\_\\_\\_\\_\\_\\_\\_\\__"
    },
    {
        "type": "paragraph",
        "text_fr": "<!-- image -->",
        "text_en": "<!-- image -->"
    },
    {
        "type": "paragraph",
        "text_fr": "<!-- image -->",
        "text_en": "<!-- image -->"
    },
    {
        "type": "paragraph",
        "text_fr": "<!-- image -->",
        "text_en": "<!-- image -->"
    },
    {
        "type": "paragraph",
        "text_fr": "Réaffirmant ses  résolutions  53/199  du  15  décembre  1998  et  61/185  du 20 décembre 2006 sur la proclamation d'années internationales, et la résolution 1980/67 du Conseil économique et social, en date du 25 juillet 1980, sur les années internationales et les anniversaires,",
        "text_en": "Reaffirming its resolutions 53/199 of 15 December 1998 and 61/185 of 20 December 2006 on the proclamation of international years, and Economic and Social Council resolution 1980/67 of 25 July 1980 on international years and anniversaries,"
    },
    {
        "type": "paragraph",
        "text_fr": "Attirant  l'attention sur  les  inquiétudes  que  la  propagation  et  la  prolifération exponentielles de la désinformation et de la mésinformation suscitent dans le monde, rendant  d'autant  plus  nécessaire  la  diffusion  en  temps  opportun  et  dans  plusieurs langues  d'informations  factuelles,  ciblées,  claires,  accessibles  et  fondées  sur  des données  scientifiques,  et  soulignant  qu'il  faut  que  tous  les  États  Membres  fassent front  commun  pour  relever  le  défi  que  constituent  les  informations  fausses  ou trompeuses,",
        "text_en": "Drawing attention to the concern that the exponential spread and proliferation of misinformation and misinformation are creating worldwide, making it all the more necessary to disseminate factual, focused, clear, accessible and science-based information in a timely manner and in a number of languages, and stressing the need for all Member States to work together to meet the challenge of false or misleading information,"
    },
    {
        "type": "paragraph",
        "text_fr": "Soulignant que  l'éducation  aux  médias  et  à  l'information  est  également nécessaire à la réalisation du développement durable,",
        "text_en": "Emphasizing that media and public information education is also necessary for the achievement of sustainable development,"
    },
    {
        "type": "paragraph",
        "text_fr": "Consciente qu'il  existe  d'importantes  fractures  numériques  et  inégalités  de données, dont la fracture numérique entre les genres, dans les pays et entre eux et dans  les  régions  et  entre  elles,  ainsi  qu'entre  les  pays  développés  et  les  pays  en développement, notamment en ce qui concerne l'accès à l'information, aux médias, au numérique et aux technologies des communications et leur utilisation, qui peuvent avoir  une  incidence  sur  l'aptitude  des  médias  publics,  privés  ou  autres  et  des particuliers  à  diffuser  l'information  et  à  faire  connaître  leurs  vues,  consciente également qu'il faut assurer la diversité des sources de l'information et garantir le droit de rechercher, de recevoir et de donner des informations et prenant note du fait qu'il  est  possible  de  remédier  aux  difficultés  rencontrées  dans  ce  domaine  en renforçant  les  compétences  des  individus,  notamment  dans  le  cadre  d'un apprentissage tout au long de la vie,",
        "text_en": "Recognizing that there are significant digital divides and data inequalities, including the digital divide between genders, within and among countries and regions, as well as between developed and developing countries, including with regard to access to and use of information, the media, digital and communications technologies, which may affect the ability of public, private or other media and individuals to disseminate information and to communicate their views, recognizing also the need to ensure the diversity of sources of information and the right to seek, receive and provide information, and noting that challenges in this area can be addressed by strengthening the skills of individuals, including through lifelong learning,"
    },
    {
        "type": "paragraph",
        "text_fr": "Consciente de  l'importance  de  l'accès  au  numérique,  y  compris  en  ce  qui concerne la desserte et le développement d'infrastructures et de services à haut débit, en particulier au vu de l'évolution du monde depuis la pandémie, et soulignant qu'il faut veiller à ce que tous les pays aient accès aux avantages du numérique,",
        "text_en": "Recognizing the importance of digital access, including in the provision and development of broadband infrastructure and services, in particular in the light of the changing world since the pandemic, and stressing the need to ensure that all countries have access to the benefits of digital technology,"
    },
    {
        "type": "paragraph",
        "text_fr": "Réaffirmant qu'il  faut  veiller  à  trouver  un  équilibre  de  manière  que  la  lutte contre  la  désinformation  et  la  mésinformation  favorise  la  liberté  d'expression  et l'accès à l'information au lieu de leur porter atteinte, et constatant que l'éducation aux médias et à l'information peut aider à atteindre cet équilibre en sensibilisant les individus à la question et en mettant l'accent sur leur autonomisation,",
        "text_en": "Reaffirming the need to strike a balance in order to ensure that the fight against misinformation and misinformation promotes freedom of expression and access to information rather than undermines them, and recognizing that media and information education can help achieve this balance by raising awareness and enhancing the empowerment of individuals,"
    },
    {
        "type": "paragraph",
        "text_fr": "Prenant note de  la  déclaration  du  Président  de  sa  soixante-quinzième  session sur les pratiques exemplaires à adopter face à l'« infodémie »,",
        "text_en": "Taking note of the statement by the President at its seventy-fifth session on best practices in the face of \"infraredemia\","
    },
    {
        "type": "paragraph",
        "text_fr": "Prenant note également de la déclaration interrégionale sur l'infodémie dans le contexte  de  la  maladie  à  coronavirus  2019  (COVID-19),  à  laquelle  ont  souscrit 130 États Membres ainsi qu'un État observateur et un Observateur permanent,",
        "text_en": "Taking note also of the Interregional Declaration on Infodaemia in the Context of Coronavirus Disease 2019 (COVID-19), which was endorsed by 130 Member States, as well as one Observer State and one Permanent Observer,"
    },
    {
        "type": "paragraph",
        "text_fr": "Prenant note en outre du message du Secrétaire général publié à l'occasion de la conférence de haut niveau sur les dangers de la désinformation et les moyens de s'attaquer  aux  informations  fallacieuses  et  de  protéger  la  santé  à  l'ère  de  la  postvérité,",
        "text_en": "Taking note further of the message of the Secretary-General issued on the occasion of the high-level conference on the dangers of misinformation and ways to address false information and protect health in the post-truth era,"
    },
    {
        "type": "paragraph",
        "text_fr": "Prenant note de la Stratégie et du Plan d'action des Nations Unies pour la lutte contre les discours de haine, dans laquelle il est proposé de consolider les partenariats existants  avec  les  nouveaux  médias  et  les  médias  traditionnels  et  d'en  établir  de nouveaux afin de promouvoir les valeurs de la tolérance, de la non-discrimination, du pluralisme et de la liberté d'opinion et d'expression, et de lutter contre les discours de haine,",
        "text_en": "Taking note of the United Nations Strategy and Plan of Action to Combat Hate Speech, in which it is proposed that existing partnerships with new media and traditional media be strengthened and further developed to promote the values of tolerance, non-discrimination, pluralism and freedom of opinion and expression, and to combat hate speech,"
    },
    {
        "type": "paragraph",
        "text_fr": "Appréciant l'action menée par le système des Nations Unies pour aider à lutter contre  la  prolifération  de  la  mésinformation  et  de  la  désinformation,  notamment durant  la  pandémie  de  COVID-19,  en  partageant  dans  plusieurs  langues  des informations précises, actuelles et pertinentes, comme en témoignent la campagne de communication sur la riposte à la COVID-19 du Département de la communication globale  du  Secrétariat,  en  particulier  la  campagne  « Verified »  annoncée  par  le Secrétaire  général  en  avril  2020,  et  la  déclaration  conjointe  de  l'Organisation mondiale  de  la  Santé,  de  l'Organisation  des  Nations  Unies,  du  Fonds  des  Nations Unies pour l'enfance, du Programme des Nations Unies pour le développement, de l'Organisation  des  Nations  Unies  pour  l'éducation,  la  science  et  la  culture,  du Programme commun des Nations Unies sur le VIH/sida, de l'Union internationale des télécommunications, de l'initiative Global Pulse et de la Fédération internationale des Sociétés de la Croix-Rouge et du Croissant-Rouge intitulée « Gestion de l'infodémie sur la COVID-19 : promouvoir des comportements sains et atténuer les effets néfastes de la diffusion d'informations fausses et trompeuses »,",
        "text_en": "Appreciating the efforts of the United Nations system to help combat the proliferation of misinformation and disinformation, including during the VOCID-19 pandemic, by sharing specific, current and relevant information in a number of languages, as reflected in the communications campaign on the response to VOCID-19 of the Department of Global Communications of the Secretariat, in particular the \"Verified\" campaign announced by the Secretary-General in April 2020, and the joint statement of the World Health Organization, the United Nations, the United Nations Children's Fund, the United Nations Development Programme, the United Nations Educational, Scientific and Cultural Organization, the Joint United Nations Programme on HIV/AIDS, the International Telecommunication Union, the Global Pulse initiative and the International Federation of Red Cross and Red Crescent Societies entitled \"Management of the information technology on VOCID-19: promoting healthy behaviour and mitigating the adverse effects of the dissemination of false and misleading information\","
    },
    {
        "type": "paragraph",
        "text_fr": "Exprimant sa gratitude à tous les États Membres et aux parties prenantes ayant accueilli  la  Semaine  mondiale  de  l'éducation  aux  médias  et  à  l'information  ou participé à sa promotion,",
        "text_en": "Expressing its appreciation to all Member States and stakeholders that have hosted or participated in the promotion of World Media and Public Information Week,"
    },
    {
        "type": "paragraph",
        "text_fr": "Consciente du rôle de premier plan joué, avec le concours d'autres institutions spécialisées  des  Nations  Unies,  par  l'Organisation  des  Nations  Unies  pour l'éducation,  la  science  et  la  culture  dans  la  coordination  des  célébrations  de  la Semaine mondiale de l'éducation aux médias et à l'information dans le monde entier,",
        "text_en": "Recognizing the leading role played by the United Nations Educational, Scientific and Cultural Organization, with the assistance of other specialized agencies of the United Nations, in coordinating the observances of World Media and Public Information Week worldwide,"
    },
    {
        "type": "list",
        "items_fr": [
            "1 . Proclame la  semaine  du  24  au  31  octobre  de  chaque  année  Semaine mondiale de l'éducation aux médias et à l'information ;",
            "2. Invite tous les États Membres, les organisations concernées du système des Nations Unies, les autres organisations internationales et la société civile, notamment les  organisations  non  gouvernementales  et  le  secteur  privé,  à  célébrer  la  Semaine mondiale de l'éducation aux médias et à l'information de la manière qu'ils jugeront la  plus  appropriée,  notamment  en  s'attachant  à  organiser  des  célébrations,  des activités pédagogiques et des activités de sensibilisation du public qui s'attaquent à la question de la désinformation et de la mésinformation, dans la limite des ressources dont ils disposent ;",
            "3. Encourage tous les États Membres à élaborer et à appliquer des politiques, des  plans  d'action  et  des  stratégies  promouvant  l'éducation  aux  médias  et  à l'information, à faire davantage œuvre de sensibilisation sur la désinformation et la mésinformation et à augmenter les moyens de les prévenir et d'y résister, selon qu'il conviendra ;",
            "4. Encourage  également tous  les  États  Membres  à  tenir  compte  des perspectives des jeunes dans les politiques, stratégies et initiatives d'éducation aux médias  et  à  l'information,  et  à  associer  activement  les  jeunes  à  la  promotion  de l'éducation aux médias et à l'information ;",
            "5. Demande instamment aux États Membres de veiller à ce que leurs plans, politiques  et  stratégies  de  lutte  contre  la  désinformation  et  la  mésinformation respectent les principes d'indépendance et de pluralisme des médias et les droits à la liberté d'opinion et à la liberté d'expression ;",
            "6. Encourage les États Membres, le système des Nations Unies et toutes les autres parties prenantes à renforcer la coopération dans le domaine de l'éducation aux médias  et  à  l'information  aux  niveaux  mondial,  régional  et  national,  sous  la coordination de l'Organisation des Nations Unies pour l'éducation, la science et la culture, ainsi que les moyens de communication, et à améliorer les infrastructures des"
        ],
        "items_en": [
            "1 . Proclaims the week of 24 to 31 October of each year World Media and Information Education Week;",
            "2. Invites all Member States, relevant organizations of the United Nations system, other international organizations and civil society, including non-governmental organizations and the private sector, to observe World Media and Public Information Week in the manner they deem most appropriate, including through efforts to organize celebrations, educational activities and public awareness activities that address the issue of misinformation and misinformation, within their existing resources;",
            "3. Encourages all Member States to develop and implement policies, action plans and strategies to promote media and information literacy, to increase awareness of misinformation and misinformation and to increase the capacity to prevent and resist it, as appropriate;",
            "4. Also encourages all Member States to integrate youth perspectives into media and public information education policies, strategies and initiatives, and to actively involve young people in the promotion of media and public information education;",
            "5. Urges Member States to ensure that their plans, policies and strategies to combat misinformation and misinformation respect the principles of media independence and pluralism and the rights to freedom of opinion and freedom of expression;",
            "6. Encourages Member States, the United Nations system and all other stakeholders to strengthen cooperation in the field of media and public information education at the global, regional and national levels, under the coordination of the United Nations Educational, Scientific and Cultural Organization, as well as the means of communication, and to improve the infrastructure of the United Nations system in the field of media and public information."
        ]
    },
    {
        "type": "paragraph",
        "text_fr": "médias  et  les  technologies  des  communications  des  pays  en  développement,  en particulier concernant la formation professionnelle et la diffusion de l'information ;",
        "text_en": "the media and communications technologies of developing countries, in particular concerning vocational training and the dissemination of information;"
    },
    {
        "type": "list",
        "items_fr": [
            "7. Engage les organismes, fonds et programmes des Nations Unies à resserrer leurs liens de coopération avec l'Organisation des Nations Unies pour l'éducation, la science et la culture dans le domaine de l'éducation aux médias et à l'information et à aider les États Membres qui en font la demande à promouvoir celle-ci et à célébrer la Semaine mondiale de l'éducation aux médias et à l'information ;",
            "8. Encourage les organisations du secteur privé concernées, notamment les intermédiaires technologiques et les médias sociaux, à promouvoir l'éducation aux médias et à l'information de manière à autonomiser toutes les personnes et à faciliter l'inclusion numérique et la connectivité mondiale, et à concourir à la lutte contre la désinformation et la mésinformation ;",
            "9. Prie le Secrétaire général de porter la présente résolution à l'attention de tous les États Membres, des organismes des Nations Unies et des organisations de la société civile afin que la Semaine mondiale soit célébrée comme il convient."
        ],
        "items_en": [
            "7. Encourages the organizations, funds and programmes of the United Nations system to strengthen their cooperation with the United Nations Educational, Scientific and Cultural Organization in the field of media and public information education and to assist Member States, upon request, in the promotion of the United Nations Educational, Scientific and Cultural Organization and in the observance of World Media and Public Information Week;",
            "8. Encourages relevant private sector organizations, including technology intermediaries and social media, to promote media and information literacy so as to empower all people and facilitate digital inclusion and global connectivity, and to contribute to the fight against misinformation and misinformation;",
            "9. Requests the Secretary-General to bring the present resolution to the attention of all Member States, United Nations agencies and civil society organizations in order to ensure the proper observance of the World Week."
        ]
    },
    {
        "type": "paragraph",
        "text_fr": "58 e séance plénière 25 mars 2021",
        "text_en": "58th plenary meeting 25 March 2021"
    }
]